Metadata-Version: 2.1
Name: aur-upd
Version: 1.1.0.post1
Summary: The silent AUR package updater
Home-page: UNKNOWN
Author: Vladimir Kamensky (aka MasterSoft24)
Author-email: info@mastersoft24.ru 
License: UNKNOWN
Platform: UNKNOWN
